pywarc/__init__.py
pywarc/compression.py
pywarc/constants.py
pywarc/reader.py
pywarc/writer.py
pywarc-0.3.1.dist-info/LICENSE
pywarc-0.3.1.dist-info/LICENSE.LESSER
pywarc-0.3.1.dist-info/METADATA
pywarc-0.3.1.dist-info/WHEEL
pywarc-0.3.1.dist-info/top_level.txt
pywarc-0.3.1.dist-info/RECORD
