Metadata-Version: 2.1
Name: pywarc
Version: 0.3.1
Summary: WARC file format library
Home-page: https://github.com/5IGI0/pywarc
Author: 5IGI0
Author-email: 5IGI0@protonmail.com
Classifier: Programming Language :: Python :: 3
Classifier: Operating System :: OS Independent
Requires-Python: >=3.7
License-File: LICENSE
License-File: LICENSE.LESSER
